jellypy/__init__.py
jellypy/tierup/__init__.py
jellypy/tierup/interface.py
jellypy/tierup/irtools.py
jellypy/tierup/lib.py
jellypy/tierup/logger.py
jellypy/tierup/main.py
jellypy/tierup/panelapp.py
jellypy/tierup/data/report.schema
jellypy_tierup-0.3.3.dist-info/METADATA
jellypy_tierup-0.3.3.dist-info/WHEEL
jellypy_tierup-0.3.3.dist-info/entry_points.txt
jellypy_tierup-0.3.3.dist-info/top_level.txt
jellypy_tierup-0.3.3.dist-info/RECORD
