Metadata-Version: 2.1
Name: jellypy-tierup
Version: 0.3.3
Summary: Reanalyse Tier 3 variants
Home-page: https://github.com/NHS-NGS/JellyPy/tierup
Author: NHS Bioinformatics Group
Author-email: nana.mensah1@nhs.net
License: MIT
Platform: UNKNOWN
Classifier: Programming Language :: Python :: 3.6
Requires-Python: >=3.6.*
Requires-Dist: click (==7.0)
Requires-Dist: jellypy-pyCIPAPI (==0.2.4)
Requires-Dist: jsonschema (==3.2.0)
